[
  {
    "value": "Koushari",
    "synonyms": [
      "Koushari",
      "koushary",
      "Kushari",
      "kushary"
    ]
  },
  {
    "value": "Tamiya",
    "synonyms": [
      "Tamiya",
      "Falafel",
      "Ta\u0027meya"
    ]
  },
  {
    "value": "Hawawshi",
    "synonyms": [
      "Hawawshi",
      "Kofta bil Aish",
      "Belyash"
    ]
  },
  {
    "value": "Mulukhiyah",
    "synonyms": [
      "Mulukhiyah",
      "Egyptian Spinach Soup",
      "Mloukhieh",
      "Molokhiyya"
    ]
  },
  {
    "value": "Umm Ali",
    "synonyms": [
      "Umm Ali",
      "om Ali",
      "omm Ali"
    ]
  },
  {
    "value": "Sambosa",
    "synonyms": [
      "Sambosa",
      "Samboska"
    ]
  },
  {
    "value": "Feteer Meshaltet",
    "synonyms": [
      "Feteer Meshaltet"
    ]
  },
  {
    "value": "Mahshi",
    "synonyms": [
      "Mahshi"
    ]
  },
  {
    "value": "Konafah",
    "synonyms": [
      "Konafah",
      "kunafa"
    ]
  },
  {
    "value": "Basbosa",
    "synonyms": [
      "Basbosa",
      "Basbousa"
    ]
  }
]